MANIFEST.in
README.rst
Version
requirements.txt
setup.py
xml_xls_loader.py
xml_xls_loader.egg-info/PKG-INFO
xml_xls_loader.egg-info/SOURCES.txt
xml_xls_loader.egg-info/dependency_links.txt
xml_xls_loader.egg-info/requires.txt
xml_xls_loader.egg-info/top_level.txt