Metadata-Version: 1.1
Name: xml-xls-loader
Version: 0.0.1
Summary: Module to load a MS xml xls into a pandas DataFrame
Home-page: https://github.com/Richard-Mathie/xml_xls_loader
Author: Richard-Mathie
Author-email: richard.mathie@cantab.net
License: GPLv3
Platform: any
Classifier: Environment :: Console
Classifier: Operating System :: OS Independent
Classifier: Intended Audience :: Science/Research
Classifier: Topic :: Scientific/Engineering
Classifier: License :: OSI Approved :: GNU General Public License v3 (GPLv3)
Classifier: Operating System :: OS Independent
Classifier: Programming Language :: Python
Classifier: Programming Language :: Python :: 2
Classifier: Programming Language :: Python :: 2.7
